voken/__init__.py
voken/shell.py
voken/text_link/__init__.py
voken/text_link/hostname_pattern.pickle
voken/text_link/text_link_pattern.pickle
voken-0.3.3.dist-info/LICENSE
voken-0.3.3.dist-info/METADATA
voken-0.3.3.dist-info/WHEEL
voken-0.3.3.dist-info/top_level.txt
voken-0.3.3.dist-info/RECORD
